blok/__blok__.py
blok/__init__.py
blok/blok.py
blok/bloks/__init__.py
blok/bloks/dns_prompt.py
blok/bloks/netifaces.py
blok/bloks/services/__init__.py
blok/bloks/services/dns.py
blok/bloks/services/vscode.py
blok/bloks/vscode.py
blok/cli/__init__.py
blok/cli/builder.py
blok/cli/create.py
blok/cli/entrypoint.py
blok/cli/install/builder.py
blok/cli/install/entrypoint.py
blok/cli/magic_registry.py
blok/cli/main.py
blok/cli/up/builder.py
blok/cli/up/entrypoint.py
blok/dependency.py
blok/dependency_resolution.py
blok/diff.py
blok/errors.py
blok/io/read.py
blok/io/write.py
blok/models.py
blok/registry.py
blok/render/panel.py
blok/render/tree.py
blok/renderer.py
blok/renderers/click.py
blok/service.py
blok/tree/__init__.py
blok/tree/models.py
blok/tree/protocols.py
blok/utils.py
blok-0.1.0.dist-info/METADATA
blok-0.1.0.dist-info/WHEEL
blok-0.1.0.dist-info/entry_points.txt
blok-0.1.0.dist-info/RECORD
