Metadata-Version: 2.1
Name: blok
Version: 0.1.0
Summary: 
Author: jhnnsrs
Author-email: jhnnsrs@gmail.com
Requires-Python: >=3.9,<4.0
Classifier: Programming Language :: Python :: 3
Classifier: Programming Language :: Python :: 3.9
Classifier: Programming Language :: Python :: 3.10
Classifier: Programming Language :: Python :: 3.11
Classifier: Programming Language :: Python :: 3.12
Provides-Extra: all
Provides-Extra: cookiecutter
Requires-Dist: cryptography (>=40.0.8) ; (python_version >= "3.8" and python_version < "4.0") and (extra == "all")
Requires-Dist: inquirer (>=3.3.0,<4.0.0)
Requires-Dist: namegenerator (>=1.0.6) ; (python_version >= "3.8" and python_version < "4.0") and (extra == "all")
Requires-Dist: netifaces (>=0.11.0) ; (python_version >= "3.8" and python_version < "4.0") and (extra == "all")
Requires-Dist: pyyaml (>=6.0.1,<7.0.0)
